gold_fifo_tax/__init__.py
gold_fifo_tax/cli.py
gold_fifo_tax/core.py
gold_fifo_tax-0.1.0.dist-info/licenses/LICENSE
gold_fifo_tax-0.1.0.dist-info/METADATA
gold_fifo_tax-0.1.0.dist-info/WHEEL
gold_fifo_tax-0.1.0.dist-info/entry_points.txt
gold_fifo_tax-0.1.0.dist-info/top_level.txt
gold_fifo_tax-0.1.0.dist-info/RECORD
